dash_chakraui_components/AspectRatio.py
dash_chakraui_components/Box.py
dash_chakraui_components/Breadcrumb.py
dash_chakraui_components/BreadcrumbItem.py
dash_chakraui_components/BreadcrumbLink.py
dash_chakraui_components/Button.py
dash_chakraui_components/Center.py
dash_chakraui_components/ChakraProvider.py
dash_chakraui_components/Checkbox.py
dash_chakraui_components/Circle.py
dash_chakraui_components/Code.py
dash_chakraui_components/Container.py
dash_chakraui_components/DashChakrauiComponents.py
dash_chakraui_components/Flex.py
dash_chakraui_components/FormControl.py
dash_chakraui_components/Grid copy.py
dash_chakraui_components/Grid.py
dash_chakraui_components/GridItem.py
dash_chakraui_components/Heading.py
dash_chakraui_components/Icon.py
dash_chakraui_components/Input.py
dash_chakraui_components/Link.py
dash_chakraui_components/Select.py
dash_chakraui_components/Slider.py
dash_chakraui_components/Spacer.py
dash_chakraui_components/Square.py
dash_chakraui_components/Stack.py
dash_chakraui_components/Stat.py
dash_chakraui_components/Switch.py
dash_chakraui_components/Text.py
dash_chakraui_components/Textarea.py
dash_chakraui_components/Wrap.py
dash_chakraui_components/WrapItem.py
dash_chakraui_components/__init__.py
dash_chakraui_components/_imports_.py
dash_chakraui_components/dash_chakraui_components.min.js
dash_chakraui_components/dash_chakraui_components.min.js.map
dash_chakraui_components/metadata.json
dash_chakraui_components/package-info.json
dash_chakraui_components-0.0.8.dist-info/LICENSE
dash_chakraui_components-0.0.8.dist-info/METADATA
dash_chakraui_components-0.0.8.dist-info/WHEEL
dash_chakraui_components-0.0.8.dist-info/top_level.txt
dash_chakraui_components-0.0.8.dist-info/RECORD
