Metadata-Version: 2.1
Name: dash-chakraui-components
Version: 0.0.8
Summary: Chakra UI components for Dash
Home-page: https://github.com/jlfsjunior/dash_chakraui_components#readme
Author: José Luiz Ferreira <jlfsjunior@gmail.com>
License: MIT
Project-URL: Bug Tracker, https://github.com/jlfsjunior/dash_chakraui_components/issues
Platform: UNKNOWN
Classifier: Programming Language :: Python :: 3
Classifier: License :: OSI Approved :: MIT License
Classifier: Operating System :: OS Independent
Classifier: Framework :: Dash
License-File: LICENSE
